kassette/__init__.py
kassette/__version__.py
kassette-0.0.1.dist-info/METADATA
kassette-0.0.1.dist-info/WHEEL
kassette-0.0.1.dist-info/top_level.txt
kassette-0.0.1.dist-info/RECORD
