Metadata-Version: 2.4
Name: kassette
Version: 0.0.1
Summary: Kassette Python SDK
Author-email: Kasset <maintainers@kasset.dev>
License-Expression: Apache-2.0
Classifier: Development Status :: 1 - Planning
Classifier: Intended Audience :: Developers
Classifier: Programming Language :: Python :: 3
Requires-Python: >=3.9
